firegex/__init__.py
firegex/__main__.py
firegex/cli.py
firegex/nfproxy/__init__.py
firegex/nfproxy/internals/__init__.py
firegex/nfproxy/internals/data.py
firegex/nfproxy/internals/exceptions.py
firegex/nfproxy/internals/models.py
firegex/nfproxy/models/__init__.py
firegex/nfproxy/models/http.py
firegex/nfproxy/models/tcp.py
firegex/nfproxy/proxysim/__init__.py
firegex-3.4.11.data/scripts/fgex
firegex-3.4.11.dist-info/METADATA
firegex-3.4.11.dist-info/WHEEL
firegex-3.4.11.dist-info/top_level.txt
firegex-3.4.11.dist-info/RECORD
